[{"x": 410, "y": 4, "label_id": 1}, {"x": 153, "y": 74, "label_id": 1}, {"x": 371, "y": 103, "label_id": 1}, {"x": 949, "y": 117, "label_id": 1}, {"x": 335, "y": 136, "label_id": 1}, {"x": 232, "y": 153, "label_id": 1}, {"x": 443, "y": 342, "label_id": 1}, {"x": 808, "y": 918, "label_id": 1}, {"x": 170, "y": 9, "label_id": 2}, {"x": 1206, "y": 26, "label_id": 2}, {"x": 105, "y": 175, "label_id": 2}, {"x": 23, "y": 218, "label_id": 2}, {"x": 136, "y": 251, "label_id": 2}, {"x": 91, "y": 335, "label_id": 2}, {"x": 767, "y": 1168, "label_id": 2}, {"x": 564, "y": 767, "label_id": 3}, {"x": 1182, "y": 375, "label_id": 3}, {"x": 1217, "y": 440, "label_id": 3}, {"x": 1027, "y": 363, "label_id": 3}, {"x": 866, "y": 272, "label_id": 3}, {"x": 754, "y": 294, "label_id": 3}, {"x": 656, "y": 1105, "label_id": 3}, {"x": 475, "y": 1019, "label_id": 3}, {"x": 531, "y": 940, "label_id": 3}, {"x": 601, "y": 941, "label_id": 3}, {"x": 754, "y": 1214, "label_id": 3}, {"x": 315, "y": 949, "label_id": 3}, {"x": 817, "y": 989, "label_id": 3}, {"x": 427, "y": 1016, "label_id": 3}, {"x": 793, "y": 707, "label_id": 3}, {"x": 60, "y": 1097, "label_id": 3}, {"x": 287, "y": 585, "label_id": 3}, {"x": 248, "y": 557, "label_id": 3}, {"x": 682, "y": 909, "label_id": 3}, {"x": 413, "y": 895, "label_id": 3}, {"x": 1214, "y": 789, "label_id": 3}, {"x": 296, "y": 365, "label_id": 3}]