[{"x": 658, "y": 100, "label_id": 1}, {"x": 769, "y": 171, "label_id": 1}, {"x": 551, "y": 221, "label_id": 1}, {"x": 796, "y": 52, "label_id": 1}, {"x": 814, "y": 310, "label_id": 1}, {"x": 753, "y": 305, "label_id": 1}, {"x": 656, "y": 368, "label_id": 1}, {"x": 571, "y": 400, "label_id": 1}, {"x": 612, "y": 304, "label_id": 1}, {"x": 524, "y": 322, "label_id": 1}, {"x": 663, "y": 467, "label_id": 1}, {"x": 534, "y": 544, "label_id": 1}, {"x": 731, "y": 723, "label_id": 1}, {"x": 817, "y": 629, "label_id": 1}, {"x": 943, "y": 697, "label_id": 1}, {"x": 1140, "y": 639, "label_id": 1}, {"x": 1189, "y": 702, "label_id": 1}, {"x": 1200, "y": 573, "label_id": 1}, {"x": 1116, "y": 413, "label_id": 1}, {"x": 1030, "y": 380, "label_id": 1}, {"x": 1086, "y": 187, "label_id": 1}, {"x": 353, "y": 259, "label_id": 1}, {"x": 338, "y": 636, "label_id": 1}, {"x": 308, "y": 741, "label_id": 1}, {"x": 169, "y": 1096, "label_id": 1}, {"x": 216, "y": 1176, "label_id": 1}, {"x": 304, "y": 1095, "label_id": 1}, {"x": 389, "y": 1049, "label_id": 1}, {"x": 331, "y": 1166, "label_id": 1}, {"x": 461, "y": 909, "label_id": 1}, {"x": 524, "y": 960, "label_id": 1}, {"x": 567, "y": 961, "label_id": 1}, {"x": 502, "y": 1060, "label_id": 1}, {"x": 752, "y": 1167, "label_id": 1}, {"x": 836, "y": 1191, "label_id": 1}, {"x": 881, "y": 1215, "label_id": 1}, {"x": 1102, "y": 1099, "label_id": 1}, {"x": 1117, "y": 990, "label_id": 1}, {"x": 891, "y": 1018, "label_id": 1}, {"x": 735, "y": 863, "label_id": 1}, {"x": 61, "y": 930, "label_id": 1}, {"x": 284, "y": 1040, "label_id": 1}, {"x": 201, "y": 1014, "label_id": 1}, {"x": 683, "y": 228, "label_id": 1}, {"x": 728, "y": 421, "label_id": 1}, {"x": 814, "y": 462, "label_id": 1}, {"x": 1158, "y": 324, "label_id": 1}, {"x": 636, "y": 890, "label_id": 1}, {"x": 303, "y": 229, "label_id": 1}, {"x": 817, "y": 211, "label_id": 1}, {"x": 930, "y": 273, "label_id": 1}, {"x": 477, "y": 182, "label_id": 2}, {"x": 693, "y": 141, "label_id": 2}, {"x": 631, "y": 519, "label_id": 2}, {"x": 869, "y": 521, "label_id": 2}, {"x": 1051, "y": 569, "label_id": 2}, {"x": 1090, "y": 720, "label_id": 2}, {"x": 841, "y": 774, "label_id": 2}, {"x": 798, "y": 852, "label_id": 2}, {"x": 879, "y": 677, "label_id": 2}, {"x": 853, "y": 579, "label_id": 2}, {"x": 1045, "y": 217, "label_id": 2}, {"x": 1004, "y": 261, "label_id": 2}, {"x": 1067, "y": 315, "label_id": 2}, {"x": 1011, "y": 1089, "label_id": 2}, {"x": 914, "y": 1132, "label_id": 2}, {"x": 934, "y": 1187, "label_id": 2}, {"x": 1054, "y": 1137, "label_id": 2}, {"x": 1132, "y": 1175, "label_id": 2}, {"x": 706, "y": 1102, "label_id": 2}, {"x": 713, "y": 1215, "label_id": 2}, {"x": 381, "y": 957, "label_id": 2}, {"x": 90, "y": 1056, "label_id": 2}, {"x": 198, "y": 917, "label_id": 2}, {"x": 230, "y": 803, "label_id": 2}, {"x": 153, "y": 720, "label_id": 2}, {"x": 209, "y": 734, "label_id": 2}, {"x": 169, "y": 394, "label_id": 2}, {"x": 93, "y": 389, "label_id": 2}, {"x": 385, "y": 378, "label_id": 2}, {"x": 325, "y": 313, "label_id": 2}, {"x": 284, "y": 346, "label_id": 2}, {"x": 221, "y": 244, "label_id": 2}, {"x": 477, "y": 356, "label_id": 2}, {"x": 606, "y": 574, "label_id": 2}, {"x": 569, "y": 660, "label_id": 2}, {"x": 135, "y": 1181, "label_id": 2}, {"x": 416, "y": 701, "label_id": 2}]