[{"x": 997, "y": 146, "label_id": 1}, {"x": 901, "y": 187, "label_id": 1}, {"x": 791, "y": 9, "label_id": 2}, {"x": 899, "y": 62, "label_id": 2}, {"x": 357, "y": 160, "label_id": 2}, {"x": 1019, "y": 199, "label_id": 2}, {"x": 865, "y": 242, "label_id": 2}, {"x": 707, "y": 244, "label_id": 2}, {"x": 537, "y": 287, "label_id": 2}, {"x": 894, "y": 333, "label_id": 2}, {"x": 829, "y": 342, "label_id": 2}, {"x": 700, "y": 422, "label_id": 2}, {"x": 849, "y": 431, "label_id": 2}, {"x": 1196, "y": 434, "label_id": 2}, {"x": 285, "y": 532, "label_id": 2}, {"x": 1024, "y": 544, "label_id": 2}, {"x": 1172, "y": 642, "label_id": 2}, {"x": 191, "y": 748, "label_id": 2}, {"x": 57, "y": 1045, "label_id": 2}]