[{"x": 940, "y": 376, "label_id": 1}, {"x": 1170, "y": 501, "label_id": 1}, {"x": 801, "y": 539, "label_id": 1}, {"x": 846, "y": 635, "label_id": 1}, {"x": 980, "y": 661, "label_id": 1}, {"x": 364, "y": 705, "label_id": 1}, {"x": 498, "y": 973, "label_id": 1}, {"x": 215, "y": 1064, "label_id": 1}, {"x": 163, "y": 1160, "label_id": 1}, {"x": 1184, "y": 139, "label_id": 2}, {"x": 681, "y": 532, "label_id": 2}, {"x": 587, "y": 630, "label_id": 2}, {"x": 724, "y": 685, "label_id": 2}, {"x": 568, "y": 904, "label_id": 2}, {"x": 143, "y": 916, "label_id": 2}, {"x": 412, "y": 1026, "label_id": 2}, {"x": 342, "y": 1036, "label_id": 2}, {"x": 55, "y": 1153, "label_id": 2}, {"x": 1050, "y": 1170, "label_id": 2}, {"x": 46, "y": 881, "label_id": 1}]