[{"x": 251, "y": 299, "label_id": 1}, {"x": 69, "y": 318, "label_id": 1}, {"x": 700, "y": 462, "label_id": 1}, {"x": 443, "y": 642, "label_id": 1}, {"x": 460, "y": 642, "label_id": 1}, {"x": 707, "y": 741, "label_id": 1}, {"x": 515, "y": 846, "label_id": 1}, {"x": 345, "y": 877, "label_id": 1}, {"x": 14, "y": 899, "label_id": 1}, {"x": 1076, "y": 913, "label_id": 1}, {"x": 1194, "y": 937, "label_id": 1}, {"x": 124, "y": 980, "label_id": 1}, {"x": 1081, "y": 26, "label_id": 2}, {"x": 117, "y": 28, "label_id": 2}, {"x": 23, "y": 33, "label_id": 2}, {"x": 669, "y": 81, "label_id": 2}, {"x": 134, "y": 112, "label_id": 2}, {"x": 326, "y": 131, "label_id": 2}, {"x": 426, "y": 182, "label_id": 2}, {"x": 815, "y": 247, "label_id": 2}, {"x": 167, "y": 328, "label_id": 2}, {"x": 664, "y": 345, "label_id": 2}, {"x": 271, "y": 381, "label_id": 2}, {"x": 148, "y": 424, "label_id": 2}, {"x": 259, "y": 422, "label_id": 2}, {"x": 175, "y": 462, "label_id": 2}, {"x": 239, "y": 575, "label_id": 2}, {"x": 602, "y": 637, "label_id": 2}, {"x": 664, "y": 666, "label_id": 2}, {"x": 91, "y": 791, "label_id": 2}, {"x": 973, "y": 813, "label_id": 2}, {"x": 215, "y": 832, "label_id": 2}, {"x": 568, "y": 901, "label_id": 2}, {"x": 419, "y": 956, "label_id": 2}, {"x": 251, "y": 964, "label_id": 2}, {"x": 1074, "y": 997, "label_id": 2}, {"x": 371, "y": 1024, "label_id": 2}, {"x": 942, "y": 1076, "label_id": 2}, {"x": 88, "y": 1117, "label_id": 2}, {"x": 1146, "y": 1120, "label_id": 2}, {"x": 952, "y": 1141, "label_id": 2}, {"x": 107, "y": 1182, "label_id": 2}, {"x": 1012, "y": 1204, "label_id": 2}, {"x": 948, "y": 1009, "label_id": 1}, {"x": 1146, "y": 1198, "label_id": 1}, {"x": 1156, "y": 1046, "label_id": 1}, {"x": 1156, "y": 24, "label_id": 1}]