[{"x": 1169, "y": 228, "label_id": 1}, {"x": 731, "y": 267, "label_id": 1}, {"x": 1124, "y": 85, "label_id": 1}, {"x": 1078, "y": 515, "label_id": 1}, {"x": 756, "y": 508, "label_id": 1}, {"x": 690, "y": 869, "label_id": 1}, {"x": 758, "y": 847, "label_id": 1}, {"x": 626, "y": 812, "label_id": 1}, {"x": 893, "y": 1218, "label_id": 1}, {"x": 547, "y": 1161, "label_id": 1}, {"x": 412, "y": 901, "label_id": 1}, {"x": 432, "y": 498, "label_id": 1}, {"x": 854, "y": 66, "label_id": 2}, {"x": 766, "y": 108, "label_id": 2}, {"x": 761, "y": 34, "label_id": 2}, {"x": 631, "y": 22, "label_id": 2}, {"x": 623, "y": 98, "label_id": 2}, {"x": 977, "y": 110, "label_id": 2}, {"x": 1041, "y": 417, "label_id": 2}, {"x": 1181, "y": 591, "label_id": 2}, {"x": 864, "y": 147, "label_id": 2}, {"x": 736, "y": 176, "label_id": 2}, {"x": 709, "y": 361, "label_id": 2}, {"x": 655, "y": 319, "label_id": 2}, {"x": 1161, "y": 781, "label_id": 2}]