[{"x": 1028, "y": 542, "label_id": 1}, {"x": 875, "y": 671, "label_id": 1}, {"x": 1038, "y": 834, "label_id": 1}, {"x": 992, "y": 954, "label_id": 1}, {"x": 980, "y": 1004, "label_id": 1}, {"x": 995, "y": 1048, "label_id": 1}, {"x": 1124, "y": 1093, "label_id": 1}, {"x": 539, "y": 1163, "label_id": 1}, {"x": 801, "y": 1180, "label_id": 1}, {"x": 1012, "y": 398, "label_id": 2}, {"x": 1100, "y": 429, "label_id": 2}, {"x": 1124, "y": 489, "label_id": 2}, {"x": 1172, "y": 539, "label_id": 2}, {"x": 1076, "y": 554, "label_id": 2}, {"x": 1096, "y": 623, "label_id": 2}, {"x": 1208, "y": 623, "label_id": 2}, {"x": 1156, "y": 630, "label_id": 2}, {"x": 1129, "y": 661, "label_id": 2}, {"x": 757, "y": 700, "label_id": 2}, {"x": 544, "y": 714, "label_id": 2}, {"x": 954, "y": 719, "label_id": 2}, {"x": 834, "y": 724, "label_id": 2}, {"x": 1124, "y": 721, "label_id": 2}, {"x": 594, "y": 743, "label_id": 2}, {"x": 990, "y": 748, "label_id": 2}, {"x": 1093, "y": 745, "label_id": 2}, {"x": 1028, "y": 769, "label_id": 2}, {"x": 942, "y": 774, "label_id": 2}, {"x": 1208, "y": 801, "label_id": 2}, {"x": 906, "y": 820, "label_id": 2}, {"x": 1124, "y": 827, "label_id": 2}, {"x": 1170, "y": 837, "label_id": 2}, {"x": 803, "y": 870, "label_id": 2}, {"x": 1206, "y": 885, "label_id": 2}, {"x": 1062, "y": 894, "label_id": 2}, {"x": 798, "y": 923, "label_id": 2}, {"x": 685, "y": 971, "label_id": 2}, {"x": 1036, "y": 1000, "label_id": 2}, {"x": 1091, "y": 1002, "label_id": 2}, {"x": 906, "y": 1019, "label_id": 2}, {"x": 887, "y": 1048, "label_id": 2}, {"x": 1163, "y": 1060, "label_id": 2}, {"x": 959, "y": 1091, "label_id": 2}, {"x": 1172, "y": 1110, "label_id": 2}, {"x": 673, "y": 1139, "label_id": 2}, {"x": 870, "y": 1151, "label_id": 2}, {"x": 1213, "y": 1160, "label_id": 2}, {"x": 1175, "y": 1168, "label_id": 2}, {"x": 88, "y": 1180, "label_id": 2}, {"x": 501, "y": 1189, "label_id": 2}, {"x": 901, "y": 1201, "label_id": 2}, {"x": 1196, "y": 1206, "label_id": 2}, {"x": 554, "y": 1213, "label_id": 2}, {"x": 580, "y": 799, "label_id": 2}, {"x": 788, "y": 766, "label_id": 2}, {"x": 678, "y": 703, "label_id": 1}, {"x": 725, "y": 674, "label_id": 1}, {"x": 765, "y": 632, "label_id": 3}, {"x": 647, "y": 650, "label_id": 3}, {"x": 752, "y": 976, "label_id": 3}, {"x": 730, "y": 1018, "label_id": 3}, {"x": 890, "y": 766, "label_id": 3}, {"x": 1156, "y": 424, "label_id": 3}, {"x": 1187, "y": 429, "label_id": 3}, {"x": 808, "y": 632, "label_id": 3}, {"x": 984, "y": 493, "label_id": 3}, {"x": 1076, "y": 491, "label_id": 2}, {"x": 837, "y": 839, "label_id": 2}]