[{"x": 861, "y": 9, "label_id": 1}, {"x": 1048, "y": 11, "label_id": 1}, {"x": 959, "y": 67, "label_id": 1}, {"x": 318, "y": 71, "label_id": 1}, {"x": 223, "y": 79, "label_id": 1}, {"x": 609, "y": 81, "label_id": 1}, {"x": 724, "y": 115, "label_id": 1}, {"x": 513, "y": 143, "label_id": 1}, {"x": 1177, "y": 158, "label_id": 1}, {"x": 342, "y": 184, "label_id": 1}, {"x": 781, "y": 314, "label_id": 1}, {"x": 1028, "y": 323, "label_id": 1}, {"x": 1105, "y": 333, "label_id": 1}, {"x": 496, "y": 354, "label_id": 1}, {"x": 458, "y": 429, "label_id": 1}, {"x": 297, "y": 441, "label_id": 1}, {"x": 139, "y": 585, "label_id": 1}, {"x": 402, "y": 635, "label_id": 1}, {"x": 719, "y": 642, "label_id": 1}, {"x": 112, "y": 736, "label_id": 1}, {"x": 455, "y": 834, "label_id": 1}, {"x": 206, "y": 841, "label_id": 1}, {"x": 426, "y": 916, "label_id": 1}, {"x": 1148, "y": 954, "label_id": 1}, {"x": 400, "y": 968, "label_id": 1}, {"x": 961, "y": 973, "label_id": 1}, {"x": 71, "y": 985, "label_id": 1}, {"x": 1072, "y": 1009, "label_id": 1}, {"x": 1036, "y": 1072, "label_id": 1}, {"x": 769, "y": 47, "label_id": 2}, {"x": 69, "y": 86, "label_id": 2}, {"x": 566, "y": 117, "label_id": 2}, {"x": 846, "y": 136, "label_id": 2}, {"x": 218, "y": 153, "label_id": 2}, {"x": 618, "y": 196, "label_id": 2}, {"x": 215, "y": 206, "label_id": 2}, {"x": 1139, "y": 235, "label_id": 2}, {"x": 688, "y": 237, "label_id": 2}, {"x": 354, "y": 249, "label_id": 2}, {"x": 1093, "y": 254, "label_id": 2}, {"x": 822, "y": 268, "label_id": 2}, {"x": 47, "y": 283, "label_id": 2}, {"x": 235, "y": 302, "label_id": 2}, {"x": 441, "y": 304, "label_id": 2}, {"x": 136, "y": 314, "label_id": 2}, {"x": 1177, "y": 340, "label_id": 2}, {"x": 707, "y": 383, "label_id": 2}, {"x": 561, "y": 383, "label_id": 2}, {"x": 909, "y": 386, "label_id": 2}, {"x": 398, "y": 402, "label_id": 2}, {"x": 542, "y": 436, "label_id": 2}, {"x": 254, "y": 522, "label_id": 2}, {"x": 925, "y": 539, "label_id": 2}, {"x": 513, "y": 609, "label_id": 2}, {"x": 227, "y": 616, "label_id": 2}, {"x": 628, "y": 621, "label_id": 2}, {"x": 345, "y": 640, "label_id": 2}, {"x": 537, "y": 657, "label_id": 2}, {"x": 388, "y": 688, "label_id": 2}, {"x": 909, "y": 705, "label_id": 2}, {"x": 520, "y": 705, "label_id": 2}, {"x": 683, "y": 717, "label_id": 2}, {"x": 256, "y": 726, "label_id": 2}, {"x": 853, "y": 733, "label_id": 2}, {"x": 19, "y": 753, "label_id": 2}, {"x": 918, "y": 765, "label_id": 2}, {"x": 477, "y": 767, "label_id": 2}, {"x": 669, "y": 769, "label_id": 2}, {"x": 1016, "y": 772, "label_id": 2}, {"x": 825, "y": 781, "label_id": 2}, {"x": 232, "y": 786, "label_id": 2}, {"x": 606, "y": 825, "label_id": 2}, {"x": 1093, "y": 827, "label_id": 2}, {"x": 827, "y": 834, "label_id": 2}, {"x": 261, "y": 837, "label_id": 2}, {"x": 1187, "y": 849, "label_id": 2}, {"x": 753, "y": 853, "label_id": 2}, {"x": 690, "y": 873, "label_id": 2}, {"x": 318, "y": 889, "label_id": 2}, {"x": 1014, "y": 894, "label_id": 2}, {"x": 1120, "y": 894, "label_id": 2}, {"x": 417, "y": 901, "label_id": 2}, {"x": 822, "y": 901, "label_id": 2}, {"x": 578, "y": 906, "label_id": 2}, {"x": 501, "y": 916, "label_id": 2}, {"x": 1201, "y": 923, "label_id": 2}, {"x": 31, "y": 937, "label_id": 2}, {"x": 323, "y": 942, "label_id": 2}, {"x": 184, "y": 944, "label_id": 2}, {"x": 709, "y": 964, "label_id": 2}, {"x": 131, "y": 968, "label_id": 2}, {"x": 235, "y": 968, "label_id": 2}, {"x": 302, "y": 997, "label_id": 2}, {"x": 472, "y": 997, "label_id": 2}, {"x": 789, "y": 1004, "label_id": 2}, {"x": 618, "y": 1009, "label_id": 2}, {"x": 844, "y": 1014, "label_id": 2}, {"x": 376, "y": 1024, "label_id": 2}, {"x": 1206, "y": 1031, "label_id": 2}, {"x": 328, "y": 1055, "label_id": 2}, {"x": 518, "y": 1057, "label_id": 2}, {"x": 561, "y": 1062, "label_id": 2}, {"x": 724, "y": 1079, "label_id": 2}, {"x": 79, "y": 1086, "label_id": 2}, {"x": 290, "y": 1122, "label_id": 2}, {"x": 127, "y": 1134, "label_id": 2}, {"x": 1172, "y": 1170, "label_id": 2}, {"x": 458, "y": 1168, "label_id": 2}, {"x": 916, "y": 1175, "label_id": 2}, {"x": 841, "y": 1204, "label_id": 2}, {"x": 395, "y": 820, "label_id": 3}, {"x": 270, "y": 1078, "label_id": 3}]