[{"x": 124, "y": 28, "label_id": 1}, {"x": 506, "y": 43, "label_id": 1}, {"x": 81, "y": 47, "label_id": 1}, {"x": 388, "y": 69, "label_id": 1}, {"x": 438, "y": 103, "label_id": 1}, {"x": 175, "y": 105, "label_id": 1}, {"x": 122, "y": 151, "label_id": 1}, {"x": 498, "y": 244, "label_id": 1}, {"x": 1016, "y": 295, "label_id": 1}, {"x": 1146, "y": 419, "label_id": 1}, {"x": 129, "y": 604, "label_id": 1}, {"x": 417, "y": 892, "label_id": 1}, {"x": 973, "y": 961, "label_id": 1}, {"x": 141, "y": 968, "label_id": 1}, {"x": 23, "y": 1043, "label_id": 1}, {"x": 1079, "y": 1134, "label_id": 1}, {"x": 230, "y": 465, "label_id": 2}, {"x": 324, "y": 585, "label_id": 2}, {"x": 415, "y": 249, "label_id": 2}, {"x": 270, "y": 995, "label_id": 2}, {"x": 225, "y": 711, "label_id": 2}, {"x": 493, "y": 541, "label_id": 2}, {"x": 1014, "y": 698, "label_id": 2}, {"x": 238, "y": 1104, "label_id": 2}, {"x": 260, "y": 278, "label_id": 2}]