[{"x": 832, "y": 9, "label_id": 1}, {"x": 654, "y": 31, "label_id": 1}, {"x": 865, "y": 199, "label_id": 1}, {"x": 398, "y": 235, "label_id": 1}, {"x": 369, "y": 438, "label_id": 1}, {"x": 146, "y": 853, "label_id": 1}, {"x": 508, "y": 942, "label_id": 1}, {"x": 302, "y": 1031, "label_id": 1}, {"x": 995, "y": 1064, "label_id": 1}, {"x": 664, "y": 1141, "label_id": 1}, {"x": 1021, "y": 1156, "label_id": 1}, {"x": 1139, "y": 1160, "label_id": 1}, {"x": 251, "y": 1194, "label_id": 1}, {"x": 203, "y": 1196, "label_id": 1}, {"x": 146, "y": 33, "label_id": 2}, {"x": 314, "y": 59, "label_id": 2}, {"x": 261, "y": 131, "label_id": 2}, {"x": 580, "y": 146, "label_id": 2}, {"x": 685, "y": 151, "label_id": 2}, {"x": 772, "y": 206, "label_id": 2}, {"x": 141, "y": 242, "label_id": 2}, {"x": 592, "y": 259, "label_id": 2}, {"x": 235, "y": 357, "label_id": 2}, {"x": 256, "y": 422, "label_id": 2}, {"x": 165, "y": 426, "label_id": 2}, {"x": 750, "y": 438, "label_id": 2}, {"x": 877, "y": 446, "label_id": 2}, {"x": 623, "y": 479, "label_id": 2}, {"x": 671, "y": 479, "label_id": 2}, {"x": 443, "y": 489, "label_id": 2}, {"x": 887, "y": 513, "label_id": 2}, {"x": 362, "y": 537, "label_id": 2}, {"x": 1158, "y": 997, "label_id": 2}, {"x": 474, "y": 1052, "label_id": 2}, {"x": 1136, "y": 1086, "label_id": 2}, {"x": 163, "y": 1110, "label_id": 2}, {"x": 268, "y": 1120, "label_id": 2}, {"x": 311, "y": 1170, "label_id": 2}, {"x": 1105, "y": 1199, "label_id": 2}, {"x": 496, "y": 773, "label_id": 3}]