[{"x": 424, "y": 43, "label_id": 1}, {"x": 503, "y": 59, "label_id": 1}, {"x": 614, "y": 100, "label_id": 1}, {"x": 1139, "y": 215, "label_id": 1}, {"x": 474, "y": 424, "label_id": 1}, {"x": 371, "y": 455, "label_id": 1}, {"x": 172, "y": 498, "label_id": 1}, {"x": 640, "y": 539, "label_id": 1}, {"x": 366, "y": 546, "label_id": 1}, {"x": 885, "y": 74, "label_id": 2}, {"x": 1100, "y": 100, "label_id": 2}, {"x": 1156, "y": 110, "label_id": 2}, {"x": 1055, "y": 271, "label_id": 2}, {"x": 899, "y": 314, "label_id": 2}, {"x": 791, "y": 347, "label_id": 2}, {"x": 976, "y": 366, "label_id": 2}, {"x": 1009, "y": 419, "label_id": 2}, {"x": 633, "y": 429, "label_id": 2}, {"x": 825, "y": 501, "label_id": 2}, {"x": 1187, "y": 498, "label_id": 2}, {"x": 1122, "y": 532, "label_id": 2}, {"x": 501, "y": 578, "label_id": 2}, {"x": 1060, "y": 580, "label_id": 2}, {"x": 877, "y": 594, "label_id": 2}, {"x": 937, "y": 611, "label_id": 2}, {"x": 685, "y": 630, "label_id": 2}, {"x": 554, "y": 640, "label_id": 2}, {"x": 1007, "y": 642, "label_id": 2}, {"x": 364, "y": 666, "label_id": 2}, {"x": 899, "y": 681, "label_id": 2}, {"x": 590, "y": 690, "label_id": 2}, {"x": 1127, "y": 729, "label_id": 2}, {"x": 1050, "y": 745, "label_id": 2}, {"x": 295, "y": 793, "label_id": 2}, {"x": 796, "y": 793, "label_id": 2}, {"x": 611, "y": 803, "label_id": 2}, {"x": 235, "y": 817, "label_id": 2}, {"x": 901, "y": 827, "label_id": 2}, {"x": 225, "y": 865, "label_id": 2}, {"x": 115, "y": 870, "label_id": 2}, {"x": 1040, "y": 935, "label_id": 2}, {"x": 637, "y": 961, "label_id": 2}, {"x": 1153, "y": 997, "label_id": 2}, {"x": 980, "y": 1028, "label_id": 2}, {"x": 47, "y": 1036, "label_id": 2}, {"x": 542, "y": 1048, "label_id": 2}, {"x": 1177, "y": 1067, "label_id": 2}, {"x": 1064, "y": 1074, "label_id": 2}, {"x": 621, "y": 1115, "label_id": 2}, {"x": 354, "y": 1122, "label_id": 2}, {"x": 1163, "y": 1182, "label_id": 2}, {"x": 640, "y": 1206, "label_id": 2}, {"x": 789, "y": 1176, "label_id": 2}, {"x": 249, "y": 1091, "label_id": 2}, {"x": 178, "y": 917, "label_id": 2}, {"x": 526, "y": 833, "label_id": 1}, {"x": 555, "y": 927, "label_id": 2}, {"x": 683, "y": 782, "label_id": 2}, {"x": 730, "y": 491, "label_id": 2}, {"x": 211, "y": 1005, "label_id": 1}, {"x": 762, "y": 893, "label_id": 2}, {"x": 1106, "y": 848, "label_id": 2}]