[{"x": 954, "y": 14, "label_id": 1}, {"x": 448, "y": 23, "label_id": 1}, {"x": 527, "y": 26, "label_id": 1}, {"x": 614, "y": 26, "label_id": 1}, {"x": 1098, "y": 26, "label_id": 1}, {"x": 1208, "y": 26, "label_id": 1}, {"x": 705, "y": 33, "label_id": 1}, {"x": 909, "y": 69, "label_id": 1}, {"x": 952, "y": 107, "label_id": 1}, {"x": 1026, "y": 141, "label_id": 1}, {"x": 33, "y": 187, "label_id": 1}, {"x": 1076, "y": 194, "label_id": 1}, {"x": 954, "y": 225, "label_id": 1}, {"x": 304, "y": 266, "label_id": 1}, {"x": 158, "y": 280, "label_id": 1}, {"x": 259, "y": 280, "label_id": 1}, {"x": 43, "y": 290, "label_id": 1}, {"x": 1057, "y": 292, "label_id": 1}, {"x": 1206, "y": 292, "label_id": 1}, {"x": 438, "y": 316, "label_id": 1}, {"x": 1026, "y": 340, "label_id": 1}, {"x": 232, "y": 350, "label_id": 1}, {"x": 513, "y": 354, "label_id": 1}, {"x": 170, "y": 362, "label_id": 1}, {"x": 1153, "y": 366, "label_id": 1}, {"x": 460, "y": 386, "label_id": 1}, {"x": 328, "y": 410, "label_id": 1}, {"x": 518, "y": 414, "label_id": 1}, {"x": 580, "y": 412, "label_id": 1}, {"x": 1055, "y": 422, "label_id": 1}, {"x": 115, "y": 424, "label_id": 1}, {"x": 978, "y": 429, "label_id": 1}, {"x": 649, "y": 438, "label_id": 1}, {"x": 1168, "y": 438, "label_id": 1}, {"x": 256, "y": 458, "label_id": 1}, {"x": 731, "y": 462, "label_id": 1}, {"x": 491, "y": 465, "label_id": 1}, {"x": 858, "y": 467, "label_id": 1}, {"x": 187, "y": 472, "label_id": 1}, {"x": 777, "y": 477, "label_id": 1}, {"x": 1201, "y": 486, "label_id": 1}, {"x": 625, "y": 496, "label_id": 1}, {"x": 1139, "y": 518, "label_id": 1}, {"x": 539, "y": 520, "label_id": 1}, {"x": 971, "y": 525, "label_id": 1}, {"x": 726, "y": 537, "label_id": 1}, {"x": 546, "y": 575, "label_id": 1}, {"x": 729, "y": 580, "label_id": 1}, {"x": 995, "y": 582, "label_id": 1}, {"x": 1076, "y": 604, "label_id": 1}, {"x": 661, "y": 621, "label_id": 1}, {"x": 530, "y": 640, "label_id": 1}, {"x": 1033, "y": 647, "label_id": 1}, {"x": 729, "y": 657, "label_id": 1}, {"x": 621, "y": 669, "label_id": 1}, {"x": 1129, "y": 676, "label_id": 1}, {"x": 522, "y": 702, "label_id": 1}, {"x": 580, "y": 707, "label_id": 1}, {"x": 748, "y": 721, "label_id": 1}, {"x": 14, "y": 729, "label_id": 1}, {"x": 1064, "y": 736, "label_id": 1}, {"x": 496, "y": 743, "label_id": 1}, {"x": 798, "y": 745, "label_id": 1}, {"x": 1007, "y": 755, "label_id": 1}, {"x": 55, "y": 757, "label_id": 1}, {"x": 271, "y": 774, "label_id": 1}, {"x": 949, "y": 793, "label_id": 1}, {"x": 671, "y": 798, "label_id": 1}, {"x": 1096, "y": 798, "label_id": 1}, {"x": 115, "y": 810, "label_id": 1}, {"x": 750, "y": 815, "label_id": 1}, {"x": 971, "y": 865, "label_id": 1}, {"x": 131, "y": 868, "label_id": 1}, {"x": 1129, "y": 870, "label_id": 1}, {"x": 673, "y": 887, "label_id": 1}, {"x": 844, "y": 909, "label_id": 1}, {"x": 913, "y": 911, "label_id": 1}, {"x": 1206, "y": 923, "label_id": 1}, {"x": 1081, "y": 930, "label_id": 1}, {"x": 546, "y": 949, "label_id": 1}, {"x": 316, "y": 978, "label_id": 1}, {"x": 232, "y": 1000, "label_id": 1}, {"x": 753, "y": 1024, "label_id": 1}, {"x": 378, "y": 1038, "label_id": 1}, {"x": 887, "y": 1067, "label_id": 1}, {"x": 1009, "y": 1096, "label_id": 1}, {"x": 594, "y": 1156, "label_id": 1}, {"x": 506, "y": 1158, "label_id": 1}, {"x": 330, "y": 1211, "label_id": 1}, {"x": 79, "y": 4, "label_id": 2}, {"x": 345, "y": 9, "label_id": 2}, {"x": 407, "y": 11, "label_id": 2}, {"x": 93, "y": 170, "label_id": 2}, {"x": 98, "y": 371, "label_id": 2}, {"x": 678, "y": 515, "label_id": 2}, {"x": 925, "y": 714, "label_id": 2}, {"x": 602, "y": 774, "label_id": 2}, {"x": 549, "y": 798, "label_id": 2}, {"x": 1043, "y": 827, "label_id": 2}, {"x": 16, "y": 863, "label_id": 2}, {"x": 402, "y": 897, "label_id": 2}, {"x": 765, "y": 932, "label_id": 2}, {"x": 695, "y": 937, "label_id": 2}, {"x": 465, "y": 956, "label_id": 2}, {"x": 479, "y": 1050, "label_id": 2}, {"x": 316, "y": 1069, "label_id": 2}, {"x": 69, "y": 1139, "label_id": 2}, {"x": 388, "y": 446, "label_id": 1}, {"x": 1004, "y": 304, "label_id": 1}, {"x": 572, "y": 83, "label_id": 1}, {"x": 1014, "y": 1144, "label_id": 1}, {"x": 397, "y": 1056, "label_id": 1}, {"x": 1088, "y": 483, "label_id": 1}, {"x": 49, "y": 948, "label_id": 2}]